odoo/addons/ssi_schema_parser_mixin/README.rst
odoo/addons/ssi_schema_parser_mixin/__init__.py
odoo/addons/ssi_schema_parser_mixin/__manifest__.py
odoo/addons/ssi_schema_parser_mixin/menus.xml
odoo/addons/ssi_schema_parser_mixin/i18n/ssi_schema_parser_mixin.pot
odoo/addons/ssi_schema_parser_mixin/models/__init__.py
odoo/addons/ssi_schema_parser_mixin/models/schema_parser.py
odoo/addons/ssi_schema_parser_mixin/models/schema_parser_category.py
odoo/addons/ssi_schema_parser_mixin/security/ir_model_access.xml
odoo/addons/ssi_schema_parser_mixin/static/description/icon.png
odoo/addons/ssi_schema_parser_mixin/views/schema_parser.xml
odoo/addons/ssi_schema_parser_mixin/views/schema_parser_category.xml
odoo14_addon_ssi_schema_parser_mixin-14.0.2.0.0.dist-info/METADATA
odoo14_addon_ssi_schema_parser_mixin-14.0.2.0.0.dist-info/WHEEL
odoo14_addon_ssi_schema_parser_mixin-14.0.2.0.0.dist-info/top_level.txt
odoo14_addon_ssi_schema_parser_mixin-14.0.2.0.0.dist-info/RECORD
