Metadata-Version: 2.1
Name: odoo14-addon-ssi_schema_parser_mixin
Version: 14.0.2.0.0
Summary: Generic schema parser mixin with validation support
Home-page: https://simetri-sinergi.id
Author: PT. Simetri Sinergi Indonesia
License: AGPL-3
Classifier: Programming Language :: Python
Classifier: Framework :: Odoo
Classifier: Framework :: Odoo :: 14.0
Classifier: License :: OSI Approved :: GNU Affero General Public License v3
Requires-Python: >=3.6
Requires-Dist: json-schema-for-humans
Requires-Dist: odoo14-addon-ssi-master-data-mixin
Requires-Dist: odoo14-addon-web-widget-text-markdown
Requires-Dist: odoo<14.1dev,>=14.0a
Requires-Dist: pyyaml
